ream/__init__.py
ream/actor_graph.py
ream/actor_state.py
ream/actor_version.py
ream/actors/__init__.py
ream/actors/base.py
ream/actors/dsid.py
ream/actors/enum.py
ream/actors/interface.py
ream/cache_helper.py
ream/cli_helper.py
ream/data_model_helper/__init__.py
ream/data_model_helper/_batch_file_manager.py
ream/data_model_helper/_container.py
ream/data_model_helper/_index.py
ream/data_model_helper/_io_helper.py
ream/data_model_helper/_numpy_model.py
ream/data_model_helper/_pandas_model.py
ream/data_model_helper/_polars_model.py
ream/data_model_helper/_raw_model.py
ream/dataset_helper.py
ream/fs.py
ream/helper.py
ream/params_helper.py
ream/prelude.py
ream/py.typed
ream/workspace.py
ream2-4.5.1.dist-info/LICENSE
ream2-4.5.1.dist-info/METADATA
ream2-4.5.1.dist-info/WHEEL
ream2-4.5.1.dist-info/RECORD
