Metadata-Version: 2.1
Name: ream2
Version: 4.5.1
Summary: (deprecated for libactor) An actor architecture for research software
Home-page: https://github.com/binh-vu/ream
License: MIT
Author: Binh Vu
Author-email: binh@toan2.com
Requires-Python: >=3.9,<4.0
Classifier: License :: OSI Approved :: MIT License
Classifier: Programming Language :: Python :: 3
Classifier: Programming Language :: Python :: 3.9
Classifier: Programming Language :: Python :: 3.10
Classifier: Programming Language :: Python :: 3.11
Classifier: Programming Language :: Python :: 3.12
Classifier: Programming Language :: Python :: 3.13
Requires-Dist: filelock (>=3.8.0,<4.0.0)
Requires-Dist: graph-wrapper (>=1.6.0,<2.0.0)
Requires-Dist: hugedict (>=2.12.10,<3.0.0)
Requires-Dist: loguru (>=0.7.0,<0.8.0)
Requires-Dist: orjson (>=3.9.0,<4.0.0)
Requires-Dist: pandas (>=2.1.3,<3.0.0)
Requires-Dist: polars (>=0.18.0)
Requires-Dist: pyarrow (>=17.0.0,<18.0.0)
Requires-Dist: python-slugify (>=8.0.4,<9.0.0)
Requires-Dist: serde2 (>=1.6.0,<2.0.0)
Requires-Dist: t2-yada (>=1.2.0,<2.0.0)
Requires-Dist: timer4 (>=1.0.4,<2.0.0)
Project-URL: Repository, https://github.com/binh-vu/ream
